odoo/addons/crm_stage_multi_company/README.rst
odoo/addons/crm_stage_multi_company/__init__.py
odoo/addons/crm_stage_multi_company/__manifest__.py
odoo/addons/crm_stage_multi_company/i18n/crm_stage_multi_company.pot
odoo/addons/crm_stage_multi_company/i18n/it.po
odoo/addons/crm_stage_multi_company/models/__init__.py
odoo/addons/crm_stage_multi_company/models/crm_lead.py
odoo/addons/crm_stage_multi_company/models/crm_stage.py
odoo/addons/crm_stage_multi_company/readme/CONTRIBUTORS.rst
odoo/addons/crm_stage_multi_company/readme/DESCRIPTION.rst
odoo/addons/crm_stage_multi_company/security/crm_security.xml
odoo/addons/crm_stage_multi_company/static/description/icon.png
odoo/addons/crm_stage_multi_company/static/description/index.html
odoo/addons/crm_stage_multi_company/tests/__init__.py
odoo/addons/crm_stage_multi_company/tests/test_crm_stage_multi_company.py
odoo/addons/crm_stage_multi_company/views/crm_stage.xml
odoo_addon_crm_stage_multi_company-16.0.1.0.0.4.dist-info/METADATA
odoo_addon_crm_stage_multi_company-16.0.1.0.0.4.dist-info/WHEEL
odoo_addon_crm_stage_multi_company-16.0.1.0.0.4.dist-info/top_level.txt
odoo_addon_crm_stage_multi_company-16.0.1.0.0.4.dist-info/RECORD
